odoo8_addon_l10n_it_rea-8.0.0.1.0.99.dev6-py2.7-nspkg.pth
odoo8_addon_l10n_it_rea-8.0.0.1.0.99.dev6.dist-info/DESCRIPTION.rst
odoo8_addon_l10n_it_rea-8.0.0.1.0.99.dev6.dist-info/METADATA
odoo8_addon_l10n_it_rea-8.0.0.1.0.99.dev6.dist-info/RECORD
odoo8_addon_l10n_it_rea-8.0.0.1.0.99.dev6.dist-info/WHEEL
odoo8_addon_l10n_it_rea-8.0.0.1.0.99.dev6.dist-info/metadata.json
odoo8_addon_l10n_it_rea-8.0.0.1.0.99.dev6.dist-info/namespace_packages.txt
odoo8_addon_l10n_it_rea-8.0.0.1.0.99.dev6.dist-info/top_level.txt
odoo_addons/l10n_it_rea/README.rst
odoo_addons/l10n_it_rea/__init__.py
odoo_addons/l10n_it_rea/__openerp__.py
odoo_addons/l10n_it_rea/partner_view.xml
odoo_addons/l10n_it_rea/res_partner.py
odoo_addons/l10n_it_rea/i18n/es.po
odoo_addons/l10n_it_rea/i18n/it.po
odoo_addons/l10n_it_rea/i18n/l10n_it_rea.pot
odoo_addons/l10n_it_rea/i18n/sl.po
odoo_addons/l10n_it_rea/static/description/icon.png
